asyncdbus/__init__.py
asyncdbus/auth.py
asyncdbus/constants.py
asyncdbus/errors.py
asyncdbus/introspection.py
asyncdbus/message.py
asyncdbus/message_bus.py
asyncdbus/proxy_object.py
asyncdbus/py.typed
asyncdbus/service.py
asyncdbus/signature.py
asyncdbus/validators.py
asyncdbus/_private/__init__.py
asyncdbus/_private/address.py
asyncdbus/_private/constants.py
asyncdbus/_private/marshaller.py
asyncdbus/_private/unmarshaller.py
asyncdbus/_private/util.py
asyncdbus-0.7.3.dist-info/licenses/LICENSE
asyncdbus-0.7.3.dist-info/METADATA
asyncdbus-0.7.3.dist-info/WHEEL
asyncdbus-0.7.3.dist-info/top_level.txt
asyncdbus-0.7.3.dist-info/RECORD
