Metadata-Version: 2.4
Name: asyncdbus
Version: 0.7.3
Summary: A zero-dependency async DBus library
Home-page: https://github.com/M-o-a-T/asyncdbus
Author: Matthias Urlichs
Author-email: matthias@urlichs.de
License: MIT
Classifier: Development Status :: 3 - Alpha
Classifier: Environment :: X11 Applications
Classifier: Environment :: X11 Applications :: Gnome
Classifier: Topic :: Desktop Environment :: Gnome
Classifier: Topic :: Software Development :: Embedded Systems
Classifier: Framework :: AsyncIO
Classifier: Framework :: Trio
Classifier: License :: OSI Approved :: MIT License
Classifier: Programming Language :: Python
Classifier: Programming Language :: Python :: 3
Classifier: Programming Language :: Python :: 3.7
Classifier: Programming Language :: Python :: 3.8
Classifier: Programming Language :: Python :: 3.9
Classifier: Programming Language :: Python :: Implementation :: CPython
Classifier: Programming Language :: Python :: Implementation :: PyPy
Classifier: Typing :: Typed
Requires-Python: >=3.7.0
License-File: LICENSE
Requires-Dist: anyio>=3
Dynamic: author
Dynamic: author-email
Dynamic: classifier
Dynamic: description
Dynamic: description-content-type
Dynamic: home-page
Dynamic: license
Dynamic: license-file
Dynamic: requires-dist
Dynamic: requires-python
Dynamic: summary
